
----------------------------------------------------------------------
Interpreter

code size        =    291K bytes
total space      =   1023K bytes
wasted space     =    732K bytes

# of codelets    =    269
avg codelet size =   1110 bytes


----------------------------------------------------------------------
slow signature handler  [0x000000010566b7a0, 0x000000010566bb20]  896 bytes

Could not load hsdis-amd64.dylib; library not loadable; PrintAssembly is disabled

----------------------------------------------------------------------
error exits  [0x000000010566bb60, 0x000000010566bc60]  256 bytes


----------------------------------------------------------------------
return entry points  [0x000000010566bca0, 0x000000010566d760]  6848 bytes


----------------------------------------------------------------------
invoke return entry points  [0x000000010566d7a0, 0x000000010566e0a0]  2304 bytes


----------------------------------------------------------------------
earlyret entry points  [0x000000010566e0e0, 0x0000000105671e20]  15680 bytes


----------------------------------------------------------------------
deoptimization entry points  [0x0000000105671e60, 0x0000000105680d80]  61216 bytes


----------------------------------------------------------------------
result handlers for native calls  [0x0000000105680dc0, 0x0000000105680de0]  32 bytes


----------------------------------------------------------------------
continuation entry points  [0x0000000105680e20, 0x0000000105680f20]  256 bytes


----------------------------------------------------------------------
safepoint entry points  [0x0000000105680f60, 0x00000001056824c0]  5472 bytes


----------------------------------------------------------------------
exception handling  [0x0000000105682500, 0x0000000105684400]  7936 bytes


----------------------------------------------------------------------
throw exception entrypoints  [0x0000000105684440, 0x0000000105685360]  3872 bytes


----------------------------------------------------------------------
method entry point (kind = zerolocals)  [0x00000001056853a0, 0x00000001056861a0]  3584 bytes


----------------------------------------------------------------------
method entry point (kind = zerolocals_synchronized)  [0x00000001056861e0, 0x00000001056873a0]  4544 bytes


----------------------------------------------------------------------
method entry point (kind = empty)  [0x00000001056873e0, 0x0000000105687400]  32 bytes


----------------------------------------------------------------------
method entry point (kind = accessor)  [0x0000000105687440, 0x0000000105687460]  32 bytes


----------------------------------------------------------------------
method entry point (kind = abstract)  [0x00000001056874a0, 0x0000000105687780]  736 bytes


----------------------------------------------------------------------
method entry point (kind = java_lang_math_sin)  [0x00000001056877c0, 0x0000000105687b20]  864 bytes


----------------------------------------------------------------------
method entry point (kind = java_lang_math_cos)  [0x0000000105687b60, 0x0000000105687ec0]  864 bytes


----------------------------------------------------------------------
method entry point (kind = java_lang_math_tan)  [0x0000000105687f00, 0x0000000105688260]  864 bytes


----------------------------------------------------------------------
method entry point (kind = java_lang_math_abs)  [0x00000001056882a0, 0x00000001056882c0]  32 bytes


----------------------------------------------------------------------
method entry point (kind = java_lang_math_sqrt)  [0x0000000105688300, 0x0000000105688320]  32 bytes


----------------------------------------------------------------------
method entry point (kind = java_lang_math_log)  [0x0000000105688360, 0x0000000105688380]  32 bytes


----------------------------------------------------------------------
method entry point (kind = java_lang_math_log10)  [0x00000001056883c0, 0x00000001056883e0]  32 bytes


----------------------------------------------------------------------
method entry point (kind = java_lang_math_exp)  [0x0000000105688420, 0x00000001056887e0]  960 bytes


----------------------------------------------------------------------
method entry point (kind = java_lang_math_pow)  [0x0000000105688820, 0x0000000105688d60]  1344 bytes


----------------------------------------------------------------------
method entry point (kind = java_lang_ref_reference_get)  [0x0000000105688da0, 0x0000000105688dc0]  32 bytes


----------------------------------------------------------------------
method entry point (kind = java_util_zip_CRC32_update)  [0x0000000105688e00, 0x000000010568a720]  6432 bytes


----------------------------------------------------------------------
method entry point (kind = java_util_zip_CRC32_updateBytes)  [0x000000010568a760, 0x000000010568c0a0]  6464 bytes


----------------------------------------------------------------------
method entry point (kind = java_util_zip_CRC32_updateByteBuffer)  [0x000000010568c0e0, 0x000000010568da20]  6464 bytes


----------------------------------------------------------------------
method entry point (kind = native)  [0x000000010568da60, 0x000000010568f340]  6368 bytes


----------------------------------------------------------------------
method entry point (kind = native_synchronized)  [0x000000010568f380, 0x0000000105691020]  7328 bytes


----------------------------------------------------------------------
nop  0 nop  [0x0000000105691060, 0x00000001056910c0]  96 bytes


----------------------------------------------------------------------
aconst_null  1 aconst_null  [0x0000000105691100, 0x0000000105691160]  96 bytes


----------------------------------------------------------------------
iconst_m1  2 iconst_m1  [0x00000001056911a0, 0x0000000105691200]  96 bytes


----------------------------------------------------------------------
iconst_0  3 iconst_0  [0x0000000105691240, 0x00000001056912a0]  96 bytes


----------------------------------------------------------------------
iconst_1  4 iconst_1  [0x00000001056912e0, 0x0000000105691340]  96 bytes


----------------------------------------------------------------------
iconst_2  5 iconst_2  [0x0000000105691380, 0x00000001056913e0]  96 bytes


----------------------------------------------------------------------
iconst_3  6 iconst_3  [0x0000000105691420, 0x0000000105691480]  96 bytes


----------------------------------------------------------------------
iconst_4  7 iconst_4  [0x00000001056914c0, 0x0000000105691520]  96 bytes


----------------------------------------------------------------------
iconst_5  8 iconst_5  [0x0000000105691560, 0x00000001056915c0]  96 bytes


----------------------------------------------------------------------
lconst_0  9 lconst_0  [0x0000000105691600, 0x0000000105691660]  96 bytes


----------------------------------------------------------------------
lconst_1  10 lconst_1  [0x00000001056916a0, 0x0000000105691700]  96 bytes


----------------------------------------------------------------------
fconst_0  11 fconst_0  [0x0000000105691740, 0x00000001056917a0]  96 bytes


----------------------------------------------------------------------
fconst_1  12 fconst_1  [0x00000001056917e0, 0x0000000105691840]  96 bytes


----------------------------------------------------------------------
fconst_2  13 fconst_2  [0x0000000105691880, 0x00000001056918e0]  96 bytes


----------------------------------------------------------------------
dconst_0  14 dconst_0  [0x0000000105691920, 0x0000000105691980]  96 bytes


----------------------------------------------------------------------
dconst_1  15 dconst_1  [0x00000001056919c0, 0x0000000105691a20]  96 bytes


----------------------------------------------------------------------
bipush  16 bipush  [0x0000000105691a60, 0x0000000105691ac0]  96 bytes


----------------------------------------------------------------------
sipush  17 sipush  [0x0000000105691b00, 0x0000000105691b60]  96 bytes


----------------------------------------------------------------------
ldc  18 ldc  [0x0000000105691ba0, 0x0000000105691f20]  896 bytes


----------------------------------------------------------------------
ldc_w  19 ldc_w  [0x0000000105691f60, 0x0000000105692300]  928 bytes


----------------------------------------------------------------------
ldc2_w  20 ldc2_w  [0x0000000105692340, 0x00000001056923e0]  160 bytes


----------------------------------------------------------------------
iload  21 iload  [0x0000000105692420, 0x0000000105692560]  320 bytes


----------------------------------------------------------------------
lload  22 lload  [0x00000001056925a0, 0x0000000105692620]  128 bytes


----------------------------------------------------------------------
fload  23 fload  [0x0000000105692660, 0x00000001056926e0]  128 bytes


----------------------------------------------------------------------
dload  24 dload  [0x0000000105692720, 0x00000001056927c0]  160 bytes


----------------------------------------------------------------------
aload  25 aload  [0x0000000105692800, 0x0000000105692880]  128 bytes


----------------------------------------------------------------------
iload_0  26 iload_0  [0x00000001056928c0, 0x0000000105692920]  96 bytes


----------------------------------------------------------------------
iload_1  27 iload_1  [0x0000000105692960, 0x00000001056929c0]  96 bytes


----------------------------------------------------------------------
iload_2  28 iload_2  [0x0000000105692a00, 0x0000000105692a60]  96 bytes


----------------------------------------------------------------------
iload_3  29 iload_3  [0x0000000105692aa0, 0x0000000105692b00]  96 bytes


----------------------------------------------------------------------
lload_0  30 lload_0  [0x0000000105692b40, 0x0000000105692ba0]  96 bytes


----------------------------------------------------------------------
lload_1  31 lload_1  [0x0000000105692be0, 0x0000000105692c40]  96 bytes


----------------------------------------------------------------------
lload_2  32 lload_2  [0x0000000105692c80, 0x0000000105692ce0]  96 bytes


----------------------------------------------------------------------
lload_3  33 lload_3  [0x0000000105692d20, 0x0000000105692d80]  96 bytes


----------------------------------------------------------------------
fload_0  34 fload_0  [0x0000000105692dc0, 0x0000000105692e20]  96 bytes


----------------------------------------------------------------------
fload_1  35 fload_1  [0x0000000105692e60, 0x0000000105692ec0]  96 bytes


----------------------------------------------------------------------
fload_2  36 fload_2  [0x0000000105692f00, 0x0000000105692f60]  96 bytes


----------------------------------------------------------------------
fload_3  37 fload_3  [0x0000000105692fa0, 0x0000000105693000]  96 bytes


----------------------------------------------------------------------
dload_0  38 dload_0  [0x0000000105693040, 0x00000001056930a0]  96 bytes


----------------------------------------------------------------------
dload_1  39 dload_1  [0x00000001056930e0, 0x0000000105693140]  96 bytes


----------------------------------------------------------------------
dload_2  40 dload_2  [0x0000000105693180, 0x00000001056931e0]  96 bytes


----------------------------------------------------------------------
dload_3  41 dload_3  [0x0000000105693220, 0x0000000105693280]  96 bytes


----------------------------------------------------------------------
aload_0  42 aload_0  [0x00000001056932c0, 0x00000001056933e0]  288 bytes


----------------------------------------------------------------------
aload_1  43 aload_1  [0x0000000105693420, 0x0000000105693480]  96 bytes


----------------------------------------------------------------------
aload_2  44 aload_2  [0x00000001056934c0, 0x0000000105693520]  96 bytes


----------------------------------------------------------------------
aload_3  45 aload_3  [0x0000000105693560, 0x00000001056935c0]  96 bytes


----------------------------------------------------------------------
iaload  46 iaload  [0x0000000105693600, 0x0000000105693640]  64 bytes


----------------------------------------------------------------------
laload  47 laload  [0x0000000105693680, 0x00000001056936c0]  64 bytes


----------------------------------------------------------------------
faload  48 faload  [0x0000000105693700, 0x0000000105693740]  64 bytes


----------------------------------------------------------------------
daload  49 daload  [0x0000000105693780, 0x00000001056937c0]  64 bytes


----------------------------------------------------------------------
aaload  50 aaload  [0x0000000105693800, 0x00000001056938c0]  192 bytes


----------------------------------------------------------------------
baload  51 baload  [0x0000000105693900, 0x0000000105693940]  64 bytes


----------------------------------------------------------------------
caload  52 caload  [0x0000000105693980, 0x00000001056939c0]  64 bytes


----------------------------------------------------------------------
saload  53 saload  [0x0000000105693a00, 0x0000000105693a40]  64 bytes


----------------------------------------------------------------------
istore  54 istore  [0x0000000105693a80, 0x0000000105693ae0]  96 bytes


----------------------------------------------------------------------
lstore  55 lstore  [0x0000000105693b20, 0x0000000105693b80]  96 bytes


----------------------------------------------------------------------
fstore  56 fstore  [0x0000000105693bc0, 0x0000000105693c40]  128 bytes


----------------------------------------------------------------------
dstore  57 dstore  [0x0000000105693c80, 0x0000000105693d00]  128 bytes


----------------------------------------------------------------------
astore  58 astore  [0x0000000105693d40, 0x0000000105693dc0]  128 bytes


----------------------------------------------------------------------
istore_0  59 istore_0  [0x0000000105693e00, 0x0000000105693e20]  32 bytes


----------------------------------------------------------------------
istore_1  60 istore_1  [0x0000000105693e60, 0x0000000105693ea0]  64 bytes


----------------------------------------------------------------------
istore_2  61 istore_2  [0x0000000105693ee0, 0x0000000105693f20]  64 bytes


----------------------------------------------------------------------
istore_3  62 istore_3  [0x0000000105693f60, 0x0000000105693fa0]  64 bytes


----------------------------------------------------------------------
lstore_0  63 lstore_0  [0x0000000105693fe0, 0x0000000105694020]  64 bytes


----------------------------------------------------------------------
lstore_1  64 lstore_1  [0x0000000105694060, 0x00000001056940a0]  64 bytes


----------------------------------------------------------------------
lstore_2  65 lstore_2  [0x00000001056940e0, 0x0000000105694120]  64 bytes


----------------------------------------------------------------------
lstore_3  66 lstore_3  [0x0000000105694160, 0x00000001056941a0]  64 bytes


----------------------------------------------------------------------
fstore_0  67 fstore_0  [0x00000001056941e0, 0x0000000105694220]  64 bytes


----------------------------------------------------------------------
fstore_1  68 fstore_1  [0x0000000105694260, 0x00000001056942a0]  64 bytes


----------------------------------------------------------------------
fstore_2  69 fstore_2  [0x00000001056942e0, 0x0000000105694320]  64 bytes


----------------------------------------------------------------------
fstore_3  70 fstore_3  [0x0000000105694360, 0x00000001056943a0]  64 bytes


----------------------------------------------------------------------
dstore_0  71 dstore_0  [0x00000001056943e0, 0x0000000105694420]  64 bytes


----------------------------------------------------------------------
dstore_1  72 dstore_1  [0x0000000105694460, 0x00000001056944a0]  64 bytes


----------------------------------------------------------------------
dstore_2  73 dstore_2  [0x00000001056944e0, 0x0000000105694520]  64 bytes


----------------------------------------------------------------------
dstore_3  74 dstore_3  [0x0000000105694560, 0x00000001056945a0]  64 bytes


----------------------------------------------------------------------
astore_0  75 astore_0  [0x00000001056945e0, 0x0000000105694640]  96 bytes


----------------------------------------------------------------------
astore_1  76 astore_1  [0x0000000105694680, 0x00000001056946e0]  96 bytes


----------------------------------------------------------------------
astore_2  77 astore_2  [0x0000000105694720, 0x0000000105694780]  96 bytes


----------------------------------------------------------------------
astore_3  78 astore_3  [0x00000001056947c0, 0x0000000105694820]  96 bytes


----------------------------------------------------------------------
iastore  79 iastore  [0x0000000105694860, 0x00000001056948a0]  64 bytes


----------------------------------------------------------------------
lastore  80 lastore  [0x00000001056948e0, 0x0000000105694920]  64 bytes


----------------------------------------------------------------------
fastore  81 fastore  [0x0000000105694960, 0x00000001056949a0]  64 bytes


----------------------------------------------------------------------
dastore  82 dastore  [0x00000001056949e0, 0x0000000105694a20]  64 bytes


----------------------------------------------------------------------
aastore  83 aastore  [0x0000000105694a60, 0x0000000105694da0]  832 bytes


----------------------------------------------------------------------
bastore  84 bastore  [0x0000000105694de0, 0x0000000105694e20]  64 bytes


----------------------------------------------------------------------
castore  85 castore  [0x0000000105694e60, 0x0000000105694ea0]  64 bytes


----------------------------------------------------------------------
sastore  86 sastore  [0x0000000105694ee0, 0x0000000105694f20]  64 bytes


----------------------------------------------------------------------
pop  87 pop  [0x0000000105694f60, 0x0000000105694fc0]  96 bytes


----------------------------------------------------------------------
pop2  88 pop2  [0x0000000105695000, 0x0000000105695060]  96 bytes


----------------------------------------------------------------------
dup  89 dup  [0x00000001056950a0, 0x0000000105695100]  96 bytes


----------------------------------------------------------------------
dup_x1  90 dup_x1  [0x0000000105695140, 0x00000001056951a0]  96 bytes


----------------------------------------------------------------------
dup_x2  91 dup_x2  [0x00000001056951e0, 0x0000000105695260]  128 bytes


----------------------------------------------------------------------
dup2  92 dup2  [0x00000001056952a0, 0x0000000105695300]  96 bytes


----------------------------------------------------------------------
dup2_x1  93 dup2_x1  [0x0000000105695340, 0x00000001056953c0]  128 bytes


----------------------------------------------------------------------
dup2_x2  94 dup2_x2  [0x0000000105695400, 0x0000000105695480]  128 bytes


----------------------------------------------------------------------
swap  95 swap  [0x00000001056954c0, 0x0000000105695520]  96 bytes


----------------------------------------------------------------------
iadd  96 iadd  [0x0000000105695560, 0x00000001056955a0]  64 bytes


----------------------------------------------------------------------
ladd  97 ladd  [0x00000001056955e0, 0x0000000105695620]  64 bytes


----------------------------------------------------------------------
fadd  98 fadd  [0x0000000105695660, 0x00000001056956a0]  64 bytes


----------------------------------------------------------------------
dadd  99 dadd  [0x00000001056956e0, 0x0000000105695720]  64 bytes


----------------------------------------------------------------------
isub  100 isub  [0x0000000105695760, 0x00000001056957a0]  64 bytes


----------------------------------------------------------------------
lsub  101 lsub  [0x00000001056957e0, 0x0000000105695820]  64 bytes


----------------------------------------------------------------------
fsub  102 fsub  [0x0000000105695860, 0x00000001056958a0]  64 bytes


----------------------------------------------------------------------
dsub  103 dsub  [0x00000001056958e0, 0x0000000105695920]  64 bytes


----------------------------------------------------------------------
imul  104 imul  [0x0000000105695960, 0x00000001056959a0]  64 bytes


----------------------------------------------------------------------
lmul  105 lmul  [0x00000001056959e0, 0x0000000105695a20]  64 bytes


----------------------------------------------------------------------
fmul  106 fmul  [0x0000000105695a60, 0x0000000105695aa0]  64 bytes


----------------------------------------------------------------------
dmul  107 dmul  [0x0000000105695ae0, 0x0000000105695b20]  64 bytes


----------------------------------------------------------------------
idiv  108 idiv  [0x0000000105695b60, 0x0000000105695ba0]  64 bytes


----------------------------------------------------------------------
ldiv  109 ldiv  [0x0000000105695be0, 0x0000000105695c40]  96 bytes


----------------------------------------------------------------------
fdiv  110 fdiv  [0x0000000105695c80, 0x0000000105695cc0]  64 bytes


----------------------------------------------------------------------
ddiv  111 ddiv  [0x0000000105695d00, 0x0000000105695d40]  64 bytes


----------------------------------------------------------------------
irem  112 irem  [0x0000000105695d80, 0x0000000105695de0]  96 bytes


----------------------------------------------------------------------
lrem  113 lrem  [0x0000000105695e20, 0x0000000105695e80]  96 bytes


----------------------------------------------------------------------
frem  114 frem  [0x0000000105695ec0, 0x0000000105695fa0]  224 bytes


----------------------------------------------------------------------
drem  115 drem  [0x0000000105695fe0, 0x00000001056960c0]  224 bytes


----------------------------------------------------------------------
ineg  116 ineg  [0x0000000105696100, 0x0000000105696120]  32 bytes


----------------------------------------------------------------------
lneg  117 lneg  [0x0000000105696160, 0x00000001056961a0]  64 bytes


----------------------------------------------------------------------
fneg  118 fneg  [0x00000001056961e0, 0x0000000105696220]  64 bytes


----------------------------------------------------------------------
dneg  119 dneg  [0x0000000105696260, 0x00000001056962a0]  64 bytes


----------------------------------------------------------------------
ishl  120 ishl  [0x00000001056962e0, 0x0000000105696320]  64 bytes


----------------------------------------------------------------------
lshl  121 lshl  [0x0000000105696360, 0x00000001056963a0]  64 bytes


----------------------------------------------------------------------
ishr  122 ishr  [0x00000001056963e0, 0x0000000105696420]  64 bytes


----------------------------------------------------------------------
lshr  123 lshr  [0x0000000105696460, 0x00000001056964a0]  64 bytes


----------------------------------------------------------------------
iushr  124 iushr  [0x00000001056964e0, 0x0000000105696520]  64 bytes


----------------------------------------------------------------------
lushr  125 lushr  [0x0000000105696560, 0x00000001056965a0]  64 bytes


----------------------------------------------------------------------
iand  126 iand  [0x00000001056965e0, 0x0000000105696620]  64 bytes


----------------------------------------------------------------------
land  127 land  [0x0000000105696660, 0x00000001056966a0]  64 bytes


----------------------------------------------------------------------
ior  128 ior  [0x00000001056966e0, 0x0000000105696720]  64 bytes


----------------------------------------------------------------------
lor  129 lor  [0x0000000105696760, 0x00000001056967a0]  64 bytes


----------------------------------------------------------------------
ixor  130 ixor  [0x00000001056967e0, 0x0000000105696820]  64 bytes


----------------------------------------------------------------------
lxor  131 lxor  [0x0000000105696860, 0x00000001056968a0]  64 bytes


----------------------------------------------------------------------
iinc  132 iinc  [0x00000001056968e0, 0x0000000105696980]  160 bytes


----------------------------------------------------------------------
i2l  133 i2l  [0x00000001056969c0, 0x00000001056969e0]  32 bytes


----------------------------------------------------------------------
i2f  134 i2f  [0x0000000105696a20, 0x0000000105696a60]  64 bytes


----------------------------------------------------------------------
i2d  135 i2d  [0x0000000105696aa0, 0x0000000105696ae0]  64 bytes


----------------------------------------------------------------------
l2i  136 l2i  [0x0000000105696b20, 0x0000000105696b40]  32 bytes


----------------------------------------------------------------------
l2f  137 l2f  [0x0000000105696b80, 0x0000000105696bc0]  64 bytes


----------------------------------------------------------------------
l2d  138 l2d  [0x0000000105696c00, 0x0000000105696c40]  64 bytes


----------------------------------------------------------------------
f2i  139 f2i  [0x0000000105696c80, 0x0000000105696d60]  224 bytes


----------------------------------------------------------------------
f2l  140 f2l  [0x0000000105696da0, 0x0000000105696e80]  224 bytes


----------------------------------------------------------------------
f2d  141 f2d  [0x0000000105696ec0, 0x0000000105696f00]  64 bytes


----------------------------------------------------------------------
d2i  142 d2i  [0x0000000105696f40, 0x0000000105697020]  224 bytes


----------------------------------------------------------------------
d2l  143 d2l  [0x0000000105697060, 0x0000000105697140]  224 bytes


----------------------------------------------------------------------
d2f  144 d2f  [0x0000000105697180, 0x00000001056971c0]  64 bytes


----------------------------------------------------------------------
i2b  145 i2b  [0x0000000105697200, 0x0000000105697220]  32 bytes


----------------------------------------------------------------------
i2c  146 i2c  [0x0000000105697260, 0x0000000105697280]  32 bytes


----------------------------------------------------------------------
i2s  147 i2s  [0x00000001056972c0, 0x00000001056972e0]  32 bytes


----------------------------------------------------------------------
lcmp  148 lcmp  [0x0000000105697320, 0x0000000105697360]  64 bytes


----------------------------------------------------------------------
fcmpl  149 fcmpl  [0x00000001056973a0, 0x00000001056973e0]  64 bytes


----------------------------------------------------------------------
fcmpg  150 fcmpg  [0x0000000105697420, 0x0000000105697460]  64 bytes


----------------------------------------------------------------------
dcmpl  151 dcmpl  [0x00000001056974a0, 0x00000001056974e0]  64 bytes


----------------------------------------------------------------------
dcmpg  152 dcmpg  [0x0000000105697520, 0x0000000105697560]  64 bytes


----------------------------------------------------------------------
ifeq  153 ifeq  [0x00000001056975a0, 0x00000001056981c0]  3104 bytes


----------------------------------------------------------------------
ifne  154 ifne  [0x0000000105698200, 0x0000000105698e20]  3104 bytes


----------------------------------------------------------------------
iflt  155 iflt  [0x0000000105698e60, 0x0000000105699a80]  3104 bytes


----------------------------------------------------------------------
ifge  156 ifge  [0x0000000105699ac0, 0x000000010569a6e0]  3104 bytes


----------------------------------------------------------------------
ifgt  157 ifgt  [0x000000010569a720, 0x000000010569b340]  3104 bytes


----------------------------------------------------------------------
ifle  158 ifle  [0x000000010569b380, 0x000000010569bfa0]  3104 bytes


----------------------------------------------------------------------
if_icmpeq  159 if_icmpeq  [0x000000010569bfe0, 0x000000010569cc00]  3104 bytes


----------------------------------------------------------------------
if_icmpne  160 if_icmpne  [0x000000010569cc40, 0x000000010569d860]  3104 bytes


----------------------------------------------------------------------
if_icmplt  161 if_icmplt  [0x000000010569d8a0, 0x000000010569e4c0]  3104 bytes


----------------------------------------------------------------------
if_icmpge  162 if_icmpge  [0x000000010569e500, 0x000000010569f120]  3104 bytes


----------------------------------------------------------------------
if_icmpgt  163 if_icmpgt  [0x000000010569f160, 0x000000010569fd80]  3104 bytes


----------------------------------------------------------------------
if_icmple  164 if_icmple  [0x000000010569fdc0, 0x00000001056a09e0]  3104 bytes


----------------------------------------------------------------------
if_acmpeq  165 if_acmpeq  [0x00000001056a0a20, 0x00000001056a1640]  3104 bytes


----------------------------------------------------------------------
if_acmpne  166 if_acmpne  [0x00000001056a1680, 0x00000001056a22a0]  3104 bytes


----------------------------------------------------------------------
goto  167 goto  [0x00000001056a22e0, 0x00000001056a2e80]  2976 bytes


----------------------------------------------------------------------
jsr  168 jsr  [0x00000001056a2ec0, 0x00000001056a2fc0]  256 bytes


----------------------------------------------------------------------
ret  169 ret  [0x00000001056a3000, 0x00000001056a36e0]  1760 bytes


----------------------------------------------------------------------
tableswitch  170 tableswitch  [0x00000001056a3720, 0x00000001056a3840]  288 bytes


----------------------------------------------------------------------
lookupswitch  171 lookupswitch  [0x00000001056a3880, 0x00000001056a3980]  256 bytes


----------------------------------------------------------------------
ireturn  172 ireturn  [0x00000001056a39c0, 0x00000001056a43a0]  2528 bytes


----------------------------------------------------------------------
lreturn  173 lreturn  [0x00000001056a43e0, 0x00000001056a4dc0]  2528 bytes


----------------------------------------------------------------------
freturn  174 freturn  [0x00000001056a4e00, 0x00000001056a57e0]  2528 bytes


----------------------------------------------------------------------
dreturn  175 dreturn  [0x00000001056a5820, 0x00000001056a6200]  2528 bytes


----------------------------------------------------------------------
areturn  176 areturn  [0x00000001056a6240, 0x00000001056a6c00]  2496 bytes


----------------------------------------------------------------------
return  177 return  [0x00000001056a6c40, 0x00000001056a7620]  2528 bytes


----------------------------------------------------------------------
getstatic  178 getstatic  [0x00000001056a7660, 0x00000001056a7b00]  1184 bytes


----------------------------------------------------------------------
putstatic  179 putstatic  [0x00000001056a7b40, 0x00000001056a8020]  1248 bytes


----------------------------------------------------------------------
getfield  180 getfield  [0x00000001056a8060, 0x00000001056a89c0]  2400 bytes


----------------------------------------------------------------------
putfield  181 putfield  [0x00000001056a8a00, 0x00000001056a94c0]  2752 bytes


----------------------------------------------------------------------
invokevirtual  182 invokevirtual  [0x00000001056a9500, 0x00000001056a9be0]  1760 bytes


----------------------------------------------------------------------
invokespecial  183 invokespecial  [0x00000001056a9c20, 0x00000001056aa0e0]  1216 bytes


----------------------------------------------------------------------
invokestatic  184 invokestatic  [0x00000001056aa120, 0x00000001056aa5e0]  1216 bytes


----------------------------------------------------------------------
invokeinterface  185 invokeinterface  [0x00000001056aa620, 0x00000001056ab560]  3904 bytes


----------------------------------------------------------------------
invokedynamic  186 invokedynamic  [0x00000001056ab5a0, 0x00000001056abb20]  1408 bytes


----------------------------------------------------------------------
new  187 new  [0x00000001056abb60, 0x00000001056ac040]  1248 bytes


----------------------------------------------------------------------
newarray  188 newarray  [0x00000001056ac080, 0x00000001056ac320]  672 bytes


----------------------------------------------------------------------
anewarray  189 anewarray  [0x00000001056ac360, 0x00000001056ac600]  672 bytes


----------------------------------------------------------------------
arraylength  190 arraylength  [0x00000001056ac640, 0x00000001056ac660]  32 bytes


----------------------------------------------------------------------
athrow  191 athrow  [0x00000001056ac6a0, 0x00000001056ac720]  128 bytes


----------------------------------------------------------------------
checkcast  192 checkcast  [0x00000001056ac760, 0x00000001056acc40]  1248 bytes


----------------------------------------------------------------------
instanceof  193 instanceof  [0x00000001056acc80, 0x00000001056ad160]  1248 bytes


----------------------------------------------------------------------
monitorenter  194 monitorenter  [0x00000001056ad1a0, 0x00000001056ad5c0]  1056 bytes


----------------------------------------------------------------------
monitorexit  195 monitorexit  [0x00000001056ad600, 0x00000001056adba0]  1440 bytes


----------------------------------------------------------------------
wide  196 wide  [0x00000001056adbe0, 0x00000001056adca0]  192 bytes


----------------------------------------------------------------------
multianewarray  197 multianewarray  [0x00000001056adce0, 0x00000001056adfa0]  704 bytes


----------------------------------------------------------------------
ifnull  198 ifnull  [0x00000001056adfe0, 0x00000001056aec00]  3104 bytes


----------------------------------------------------------------------
ifnonnull  199 ifnonnull  [0x00000001056aec40, 0x00000001056af860]  3104 bytes


----------------------------------------------------------------------
goto_w  200 goto_w  [0x00000001056af8a0, 0x00000001056b04c0]  3104 bytes


----------------------------------------------------------------------
jsr_w  201 jsr_w  [0x00000001056b0500, 0x00000001056b0680]  384 bytes


----------------------------------------------------------------------
breakpoint  202 breakpoint  [0x00000001056b06c0, 0x00000001056b0c20]  1376 bytes


----------------------------------------------------------------------
fast_agetfield  203 fast_agetfield  [0x00000001056b0c60, 0x00000001056b0d20]  192 bytes


----------------------------------------------------------------------
fast_bgetfield  204 fast_bgetfield  [0x00000001056b0d60, 0x00000001056b0da0]  64 bytes


----------------------------------------------------------------------
fast_cgetfield  205 fast_cgetfield  [0x00000001056b0de0, 0x00000001056b0e20]  64 bytes


----------------------------------------------------------------------
fast_dgetfield  206 fast_dgetfield  [0x00000001056b0e60, 0x00000001056b0ea0]  64 bytes


----------------------------------------------------------------------
fast_fgetfield  207 fast_fgetfield  [0x00000001056b0ee0, 0x00000001056b0f20]  64 bytes


----------------------------------------------------------------------
fast_igetfield  208 fast_igetfield  [0x00000001056b0f60, 0x00000001056b0fa0]  64 bytes


----------------------------------------------------------------------
fast_lgetfield  209 fast_lgetfield  [0x00000001056b0fe0, 0x00000001056b1020]  64 bytes


----------------------------------------------------------------------
fast_sgetfield  210 fast_sgetfield  [0x00000001056b1060, 0x00000001056b10a0]  64 bytes


----------------------------------------------------------------------
fast_aputfield  211 fast_aputfield  [0x00000001056b10e0, 0x00000001056b11e0]  256 bytes


----------------------------------------------------------------------
fast_bputfield  212 fast_bputfield  [0x00000001056b1220, 0x00000001056b1280]  96 bytes


----------------------------------------------------------------------
fast_cputfield  213 fast_cputfield  [0x00000001056b12c0, 0x00000001056b1320]  96 bytes


----------------------------------------------------------------------
fast_dputfield  214 fast_dputfield  [0x00000001056b1360, 0x00000001056b13c0]  96 bytes


----------------------------------------------------------------------
fast_fputfield  215 fast_fputfield  [0x00000001056b1400, 0x00000001056b1460]  96 bytes


----------------------------------------------------------------------
fast_iputfield  216 fast_iputfield  [0x00000001056b14a0, 0x00000001056b1500]  96 bytes


----------------------------------------------------------------------
fast_lputfield  217 fast_lputfield  [0x00000001056b1540, 0x00000001056b15a0]  96 bytes


----------------------------------------------------------------------
fast_sputfield  218 fast_sputfield  [0x00000001056b15e0, 0x00000001056b1640]  96 bytes


----------------------------------------------------------------------
fast_aload_0  219 fast_aload_0  [0x00000001056b1680, 0x00000001056b16e0]  96 bytes


----------------------------------------------------------------------
fast_iaccess_0  220 fast_iaccess_0  [0x00000001056b1720, 0x00000001056b17a0]  128 bytes


----------------------------------------------------------------------
fast_aaccess_0  221 fast_aaccess_0  [0x00000001056b17e0, 0x00000001056b18e0]  256 bytes


----------------------------------------------------------------------
fast_faccess_0  222 fast_faccess_0  [0x00000001056b1920, 0x00000001056b19a0]  128 bytes


----------------------------------------------------------------------
fast_iload  223 fast_iload  [0x00000001056b19e0, 0x00000001056b1a40]  96 bytes


----------------------------------------------------------------------
fast_iload2  224 fast_iload2  [0x00000001056b1a80, 0x00000001056b1ae0]  96 bytes


----------------------------------------------------------------------
fast_icaload  225 fast_icaload  [0x00000001056b1b20, 0x00000001056b1ba0]  128 bytes


----------------------------------------------------------------------
fast_invokevfinal  226 fast_invokevfinal  [0x00000001056b1be0, 0x00000001056b1d00]  288 bytes


----------------------------------------------------------------------
fast_linearswitch  227 fast_linearswitch  [0x00000001056b1d40, 0x00000001056b1e60]  288 bytes


----------------------------------------------------------------------
fast_binaryswitch  228 fast_binaryswitch  [0x00000001056b1ea0, 0x00000001056b2000]  352 bytes


----------------------------------------------------------------------
fast_aldc  229 fast_aldc  [0x00000001056b2040, 0x00000001056b23c0]  896 bytes


----------------------------------------------------------------------
fast_aldc_w  230 fast_aldc_w  [0x00000001056b2400, 0x00000001056b2780]  896 bytes


----------------------------------------------------------------------
return_register_finalizer  231 return_register_finalizer  [0x00000001056b27c0, 0x00000001056b3400]  3136 bytes


----------------------------------------------------------------------
invokehandle  232 invokehandle  [0x00000001056b3440, 0x00000001056b39c0]  1408 bytes


----------------------------------------------------------------------
nofast_getfield  233 nofast_getfield  [0x00000001056b3a00, 0x00000001056b3ea0]  1184 bytes


----------------------------------------------------------------------
nofast_putfield  234 nofast_putfield  [0x00000001056b3ee0, 0x00000001056b43e0]  1280 bytes


----------------------------------------------------------------------
nofast_aload_0  235 nofast_aload_0  [0x00000001056b4420, 0x00000001056b4480]  96 bytes


----------------------------------------------------------------------
nofast_iload  236 nofast_iload  [0x00000001056b44c0, 0x00000001056b4520]  96 bytes


----------------------------------------------------------------------
_shouldnotreachhere  237 _shouldnotreachhere  [0x00000001056b4560, 0x00000001056b4620]  192 bytes

----------------------------------------------------------------------

